Metadata-Version: 1.1
Name: hprof2flamegraph
Version: 0.0.6
Summary: Java Flame Graphs
Home-page: https://github.com/cykl/hprof2flamegraph
Author: Clément MATHIEU
Author-email: clement+flamegraph@unportant.info
License: License :: OSI Approved :: BSD License
Platform: UNKNOWN
Classifier: Development Status :: 5 - Production/Stable
Classifier: Environment :: Console
Classifier: Intended Audience :: Developers
Classifier: Intended Audience :: System Administrators
Classifier: Operating System :: OS Independent
Classifier: Programming Language :: Python
Classifier: Programming Language :: Python :: 2
Classifier: Programming Language :: Python :: 3
Classifier: Topic :: Software Development
